mwsql/__init__.py
mwsql/dump.py
mwsql/parser.py
mwsql/utils.py
mwsql-1.0.4.dist-info/LICENSE
mwsql-1.0.4.dist-info/METADATA
mwsql-1.0.4.dist-info/WHEEL
mwsql-1.0.4.dist-info/RECORD
