Metadata-Version: 2.1
Name: mwsql
Version: 1.0.4
Summary: mwsql is a set of utilities for processing MediaWiki SQL dump data
License: GPL-3.0-or-later
Author: Slavina Stefanova
Author-email: slavina.stefanova@gmail.com
Requires-Python: >=3.9,<4.0
Classifier: License :: OSI Approved :: GNU General Public License v3 or later (GPLv3+)
Classifier: Programming Language :: Python :: 3
Classifier: Programming Language :: Python :: 3.9
Classifier: Programming Language :: Python :: 3.10
Classifier: Programming Language :: Python :: 3.11
Classifier: Programming Language :: Python :: 3.12
Requires-Dist: requests (>=2.31.0,<3.0.0)
Requires-Dist: tqdm (>=4.66.1,<5.0.0)
